{
    "quotes": [
        {
            "deductible": 50,
            "reimbursementPercentage": 80,
            "coverageLimit": 5000,
            "monthlyPrice": 49.99
        },
        {
            "deductible": 50,
            "reimbursementPercentage": 90,
            "coverageLimit": 5000,
            "monthlyPrice": 59.99
        },
        {
            "deductible": 50,
            "reimbursementPercentage": 90,
            "coverageLimit": 5000,
            "monthlyPrice": 69.99
        },
        {
            "deductible": 100,
            "reimbursementPercentage": 90,
            "coverageLimit": 5000,
            "monthlyPrice": 59.99
        },
        {
            "deductible": 250,
            "reimbursementPercentage": 90,
            "coverageLimit": 5000,
            "monthlyPrice": 69.99
        },
        {
            "deductible": 500,
            "reimbursementPercentage": 90,
            "coverageLimit": 5000,
            "monthlyPrice": 79.99
        },
        {
            "deductible": 1000,
            "reimbursementPercentage": 90,
            "coverageLimit": 10000,
            "monthlyPrice": 89.99
        },
        {
            "deductible": 1000,
            "reimbursementPercentage": 90,
            "coverageLimit": 15000,
            "monthlyPrice": 69.99
        },
        {
            "deductible": 500,
            "reimbursementPercentage": 90,
            "coverageLimit": 999999,
            "monthlyPrice": 89.99
        }
    ]
}